radtext/__init__.py
radtext/core.py
radtext/utils.py
radtext/cmd/__init__.py
radtext/cmd/bioc2cdm.py
radtext/cmd/cdm2bioc.py
radtext/cmd/cmd_utils.py
radtext/cmd/collect_neg_labels.py
radtext/cmd/csv2bioc.py
radtext/cmd/deid.py
radtext/cmd/download.py
radtext/cmd/neg.py
radtext/cmd/ner.py
radtext/cmd/parse.py
radtext/cmd/preprocess.py
radtext/cmd/split_section.py
radtext/cmd/ssplit.py
radtext/cmd/tree2dep.py
radtext/models/__init__.py
radtext/models/bioc_cdm_converter.py
radtext/models/bllipparser.py
radtext/models/constants.py
radtext/models/csv2bioc.py
radtext/models/deid.py
radtext/models/download.py
radtext/models/pipeline.py
radtext/models/preprocess_spacy.py
radtext/models/preprocess_stanza.py
radtext/models/sentence_split_nltk.py
radtext/models/tree2dep.py
radtext/models/neg/__init__.py
radtext/models/neg/collect_neg_labels.py
radtext/models/neg/match_ngrex.py
radtext/models/neg/match_regex.py
radtext/models/neg/neg.py
radtext/models/neg/neg_cleanup.py
radtext/models/neg/semgraph.py
radtext/models/neg/ngrex/__init__.py
radtext/models/neg/ngrex/parser.py
radtext/models/neg/ngrex/parsetab.py
radtext/models/neg/ngrex/pattern.py
radtext/models/ner/__init__.py
radtext/models/ner/ner_regex.py
radtext/models/ner/ner_spacy.py
radtext/models/ner/radlex.py
radtext/models/ner/utils.py
radtext/models/ner/vocab.py
radtext/models/pphilter/__init__.py
radtext/models/pphilter/coordinate_map.py
radtext/models/pphilter/philter.py
radtext/models/pphilter/philter_delta.json
radtext/models/pphilter/__pycache__/__init__.cpython-38.pyc
radtext/models/pphilter/__pycache__/coordinate_map.cpython-38.pyc
radtext/models/pphilter/__pycache__/philter.cpython-38.pyc
radtext/models/pphilter/filters/__init__.py
radtext/models/pphilter/filters/blacklists/firstnames_minus_fps.json
radtext/models/pphilter/filters/blacklists/lastnames_minus_fps.json
radtext/models/pphilter/filters/regex/__init__.py
radtext/models/pphilter/filters/regex/transform_regex.py
radtext-1.0.dev8.dist-info/LICENSE
radtext-1.0.dev8.dist-info/METADATA
radtext-1.0.dev8.dist-info/WHEEL
radtext-1.0.dev8.dist-info/entry_points.txt
radtext-1.0.dev8.dist-info/top_level.txt
radtext-1.0.dev8.dist-info/RECORD
