Metadata-Version: 2.1
Name: radtext
Version: 1.0.dev8
Summary: RadText is a high-performance Python Radiology Text Analysis System.
Home-page: https://github.com/bionlplab/radtext'
Author: Yifan Peng
Author-email: yip4002@med.cornell.edu
License: MIT License
Keywords: radiology-report,text-mining,NLP
Classifier: Development Status :: 1 - Planning
Classifier: Intended Audience :: Developers
Classifier: Intended Audience :: Science/Research
Classifier: License :: OSI Approved :: MIT License
Classifier: Operating System :: POSIX :: Linux
Classifier: Topic :: Text Processing
Classifier: Topic :: Software Development
Classifier: Topic :: Scientific/Engineering :: Artificial Intelligence
Classifier: Topic :: Scientific/Engineering :: Information Analysis
Classifier: Programming Language :: Python :: 3.6
Classifier: Programming Language :: Python :: 3.7
Classifier: Programming Language :: Python :: 3.8
Requires-Python: <3.9,>=3.6
License-File: LICENSE
Requires-Dist: bioc
Requires-Dist: bllipparser
Requires-Dist: docopt
Requires-Dist: Cython
Requires-Dist: intervaltree
Requires-Dist: JPype1 (==0.6.3)
Requires-Dist: medspacy
Requires-Dist: networkx
Requires-Dist: nltk
Requires-Dist: numpy
Requires-Dist: pandas
Requires-Dist: ply
Requires-Dist: PyStanfordDependencies
Requires-Dist: PyYAML
Requires-Dist: spacy
Requires-Dist: stanza
Requires-Dist: tqdm
Requires-Dist: xlrd
Requires-Dist: cachetools
Requires-Dist: openpyxl
Provides-Extra: rest
Requires-Dist: docutils (>=0.15.2) ; extra == 'rest'
